marrow.cache-1.0.3-py2.6-nspkg.pth
marrow/cache/__init__.py
marrow/cache/compat.py
marrow/cache/exc.py
marrow/cache/model.py
marrow/cache/release.py
marrow/cache/util.py
marrow.cache-1.0.3.dist-info/DESCRIPTION.rst
marrow.cache-1.0.3.dist-info/METADATA
marrow.cache-1.0.3.dist-info/metadata.json
marrow.cache-1.0.3.dist-info/namespace_packages.txt
marrow.cache-1.0.3.dist-info/RECORD
marrow.cache-1.0.3.dist-info/top_level.txt
marrow.cache-1.0.3.dist-info/WHEEL
