Metadata-Version: 2.0
Name: marrow.cache
Version: 1.0.3
Summary: An extension to MongoEngine for memoization and document-aware caching.
Home-page: https://github.com/marrow/cache/
Author: Alice Bevan-McGregor
Author-email: alice@gothcandy.com
License: MIT
Platform: UNKNOWN
Classifier: Development Status :: 5 - Production/Stable
Classifier: Intended Audience :: Developers
Classifier: License :: OSI Approved :: MIT License
Classifier: Operating System :: OS Independent
Classifier: Programming Language :: Python
Classifier: Programming Language :: Python :: 2
Classifier: Programming Language :: Python :: 2.6
Classifier: Programming Language :: Python :: 2.7
Classifier: Programming Language :: Python :: 3
Classifier: Programming Language :: Python :: 3.2
Classifier: Programming Language :: Python :: 3.3
Classifier: Programming Language :: Python :: 3.4
Classifier: Programming Language :: Python :: Implementation :: CPython
Classifier: Programming Language :: Python :: Implementation :: PyPy
Classifier: Topic :: Software Development :: Libraries :: Python Modules
Classifier: Topic :: Utilities
Requires-Dist: pymongo (<3.0)
Requires-Dist: mongoengine (>=0.8.5)
Requires-Dist: marrow.package (<2.0)
Requires-Dist: wrapt (<2.0)
Provides-Extra: development
Requires-Dist: pytest; extra == 'development'
Requires-Dist: pytest-cov; extra == 'development'
Requires-Dist: pytest-flakes; extra == 'development'
Requires-Dist: pytest-cagoule; extra == 'development'
